ninetysix/__init__.py
ninetysix/base.py
ninetysix/parsers.py
ninetysix/plate.py
ninetysix/plates.py
ninetysix/viz.py
ninetysix/util/__init__.py
ninetysix/util/_plate_attrs.py
ninetysix/util/_validators.py
ninetysix-0.0.5.dist-info/LICENSE
ninetysix-0.0.5.dist-info/METADATA
ninetysix-0.0.5.dist-info/WHEEL
ninetysix-0.0.5.dist-info/top_level.txt
ninetysix-0.0.5.dist-info/RECORD
