Metadata-Version: 2.1
Name: ninetysix
Version: 0.0.5
Summary: A general package for tidying, annotating, and analyzing 96-well plate data.
Home-page: https://palmhjell.github.io/ninetysix/
Author: Patrick Almhjell
Author-email: palmhjell@caltech.edu
License: UNKNOWN
Platform: UNKNOWN
Classifier: Programming Language :: Python :: 3
Classifier: Operating System :: OS Independent
License-File: LICENSE
Requires-Dist: numpy
Requires-Dist: pandas
Requires-Dist: bokeh
Requires-Dist: holoviews
Requires-Dist: pandas-flavor
